[
    {
        "key": "dbln",
        "value": "%7B%2261571690853038%22%3A%222n7Rywbr%22%7D",
        "domain": "facebook.com",
        "path": "/login/device-based/",
        "hostOnly": false,
        "creation": "2025-01-16T10:06:09.929Z",
        "lastAccessed": "2025-01-16T10:06:09.929Z"
    },
    {
        "key": "datr",
        "value": "tIx_Z2hHyUBiWYZbyWwQMiAo",
        "domain": "facebook.com",
        "path": "/",
        "hostOnly": false,
        "creation": "2025-01-16T10:06:09.929Z",
        "lastAccessed": "2025-01-16T10:06:09.929Z"
    },
    {
        "key": "sb",
        "value": "tIx_Z5-u3RkWsIzx8el1ftrT",
        "domain": "facebook.com",
        "path": "/",
        "hostOnly": false,
        "creation": "2025-01-16T10:06:09.929Z",
        "lastAccessed": "2025-01-16T10:06:09.929Z"
    },
    {
        "key": "vpd",
        "value": "v1%3B494x266x2.701960802078247",
        "domain": "facebook.com",
        "path": "/",
        "hostOnly": false,
        "creation": "2025-01-16T10:06:09.929Z",
        "lastAccessed": "2025-01-16T10:06:09.929Z"
    },
    {
        "key": "ps_l",
        "value": "1",
        "domain": "facebook.com",
        "path": "/",
        "hostOnly": false,
        "creation": "2025-01-16T10:06:09.929Z",
        "lastAccessed": "2025-01-16T10:06:09.929Z"
    },
    {
        "key": "ps_n",
        "value": "1",
        "domain": "facebook.com",
        "path": "/",
        "hostOnly": false,
        "creation": "2025-01-16T10:06:09.929Z",
        "lastAccessed": "2025-01-16T10:06:09.929Z"
    },
    {
        "key": "m_pixel_ratio",
        "value": "2.701960802078247",
        "domain": "facebook.com",
        "path": "/",
        "hostOnly": false,
        "creation": "2025-01-16T10:06:09.929Z",
        "lastAccessed": "2025-01-16T10:06:09.929Z"
    },
    {
        "key": "c_user",
        "value": "61571690853038",
        "domain": "facebook.com",
        "path": "/",
        "hostOnly": false,
        "creation": "2025-01-16T10:06:09.929Z",
        "lastAccessed": "2025-01-16T10:06:09.929Z"
    },
    {
        "key": "fr",
        "value": "07Sg4mG5GtN7UQP8N.AWUEzF9pdXBbJLirV5tWN_zBSY0.Bnf4y0..AAA.0.0.BniNlA.AWUeR6bvlao",
        "domain": "facebook.com",
        "path": "/",
        "hostOnly": false,
        "creation": "2025-01-16T10:06:09.929Z",
        "lastAccessed": "2025-01-16T10:06:09.929Z"
    },
    {
        "key": "xs",
        "value": "19%3Aa_bDYJxo-aKT3g%3A2%3A1737021760%3A-1%3A-1",
        "domain": "facebook.com",
        "path": "/",
        "hostOnly": false,
        "creation": "2025-01-16T10:06:09.929Z",
        "lastAccessed": "2025-01-16T10:06:09.929Z"
    },
    {
        "key": "wd",
        "value": "360x800",
        "domain": "facebook.com",
        "path": "/",
        "hostOnly": false,
        "creation": "2025-01-16T10:06:09.929Z",
        "lastAccessed": "2025-01-16T10:06:09.930Z"
    },
    {
        "key": "locale",
        "value": "en_US",
        "domain": "facebook.com",
        "path": "/",
        "hostOnly": false,
        "creation": "2025-01-16T10:06:09.930Z",
        "lastAccessed": "2025-01-16T10:06:09.930Z"
    },
    {
        "key": "wl_cbv",
        "value": "v2%3Bclient_version%3A2713%3Btimestamp%3A1737021800",
        "domain": "facebook.com",
        "path": "/",
        "hostOnly": false,
        "creation": "2025-01-16T10:06:09.930Z",
        "lastAccessed": "2025-01-16T10:06:09.930Z"
    },
    {
        "key": "fbl_st",
        "value": "100421675%3BT%3A28950364",
        "domain": "facebook.com",
        "path": "/",
        "hostOnly": false,
        "creation": "2025-01-16T10:06:09.930Z",
        "lastAccessed": "2025-01-16T10:06:09.930Z"
    }
]